pathenv/__init__.py
pathenv/pathenv.py
pathenv-1.5.dist-info/LICENSE
pathenv-1.5.dist-info/METADATA
pathenv-1.5.dist-info/WHEEL
pathenv-1.5.dist-info/top_level.txt
pathenv-1.5.dist-info/RECORD
