Metadata-Version: 2.1
Name: pathenv
Version: 1.5
Summary: One of the best Python package to manipulate the `PATH` environment variable
Home-page: https://github.com/foxypiratecove37350/pathenv
Author: foxypiratecove37350
Author-email: foxypiratecovefnaf12@gmail.com
License: GPL-2.0
Classifier: Programming Language :: Python :: 3
Classifier: License :: OSI Approved :: GNU General Public License v2 (GPLv2)
Classifier: Operating System :: OS Independent
License-File: LICENSE
